{"leagues":{"all":"All","grandmaster":"Grandmaster","master":"Master","diamond":"Diamond","platinum":"Platinum","gold":"Gold","silver":"Silver","bronze":"Bronze"},"regions":{"global":{"long":"Global","short":"Global"},"us":{"long":"United States","short":"US"},"tw":{"long":"Taiwan","short":"TW"},"kr":{"long":"Korea","short":"KR"},"la":{"long":"Latin America","short":"LA"},"ru":{"long":"Russia","short":"RU"}},"rank_regions":{"global":{"long":"Global","short":"Global"},"eu":{"long":"Europe","short":"EU"},"sea":{"long":"Southeast Asia","short":"SEA"},"cn":{"long":"China","short":"CN"},"fea":{"long":"Korea / Taiwan","short":"KR/TW"},"am":{"long":"Americas","short":"AM"}},"expansions":{"hots":{"long":"Heart of the Swarm","short":"HoTS"},"wol":{"long":"Wings of Liberty","short":"WoL"}},"races":{"zerg":"Zerg","protoss":"Protoss","terran":"Terran","random":"Random"},"brackets":{"1v1":{"bracket":1,"random":false},"2v2t":{"bracket":2,"random":false},"3v3t":{"bracket":3,"random":false},"4v4t":{"bracket":4,"random":false},"2v2r":{"bracket":2,"random":true},"3v3r":{"bracket":3,"random":true},"4v4r":{"bracket":4,"random":true}},"season":{"year":2013,"number":6}}
